sbom4js/__init__.py
sbom4js/cli.py
sbom4js/scanner.py
sbom4js/version.py
sbom4js-0.2.1.dist-info/LICENSE
sbom4js-0.2.1.dist-info/METADATA
sbom4js-0.2.1.dist-info/WHEEL
sbom4js-0.2.1.dist-info/entry_points.txt
sbom4js-0.2.1.dist-info/top_level.txt
sbom4js-0.2.1.dist-info/RECORD
